data_collection/__init__.py
data_collection/raw_data/bengali_dialects.csv
bengali_dialects_data-0.1.0.dist-info/METADATA
bengali_dialects_data-0.1.0.dist-info/WHEEL
bengali_dialects_data-0.1.0.dist-info/top_level.txt
bengali_dialects_data-0.1.0.dist-info/RECORD
