Metadata-Version: 2.4
Name: bengali-dialects-data
Version: 0.1.0
Summary: A language dataset for Bengali Local Language Translation for digital Inclusion.
Home-page: https://www.uap-bd.edu/
Author: Md Golam Kibriya
Maintainer: Md. Shahidul Islam
Dynamic: author
Dynamic: home-page
Dynamic: maintainer
Dynamic: summary
